cimod/__init__.py
cimod/_version.py
cimod/vartype.py
cimod/__pycache__/__init__.cpython-39.opt-1.pyc
cimod/__pycache__/__init__.cpython-39.pyc
cimod/__pycache__/_version.cpython-39.opt-1.pyc
cimod/__pycache__/_version.cpython-39.pyc
cimod/__pycache__/vartype.cpython-39.opt-1.pyc
cimod/__pycache__/vartype.cpython-39.pyc
cimod/model/__init__.py
cimod/model/binary_polynomial_model.py
cimod/model/binary_quadratic_model.py
cimod/model/__pycache__/__init__.cpython-39.opt-1.pyc
cimod/model/__pycache__/__init__.cpython-39.pyc
cimod/model/__pycache__/binary_polynomial_model.cpython-39.opt-1.pyc
cimod/model/__pycache__/binary_polynomial_model.cpython-39.pyc
cimod/model/__pycache__/binary_quadratic_model.cpython-39.opt-1.pyc
cimod/model/__pycache__/binary_quadratic_model.cpython-39.pyc
cimod/model/legacy/__init__.py
cimod/model/legacy/binary_quadratic_model.py
cimod/model/legacy/__pycache__/__init__.cpython-39.opt-1.pyc
cimod/model/legacy/__pycache__/__init__.cpython-39.pyc
cimod/model/legacy/__pycache__/binary_quadratic_model.cpython-39.opt-1.pyc
cimod/model/legacy/__pycache__/binary_quadratic_model.cpython-39.pyc
cimod/utils/__init__.py
cimod/utils/decolator.py
cimod/utils/response.py
cimod/utils/__pycache__/__init__.cpython-39.opt-1.pyc
cimod/utils/__pycache__/__init__.cpython-39.pyc
cimod/utils/__pycache__/decolator.cpython-39.opt-1.pyc
cimod/utils/__pycache__/decolator.cpython-39.pyc
cimod/utils/__pycache__/response.cpython-39.opt-1.pyc
cimod/utils/__pycache__/response.cpython-39.pyc
vqa_cimod-0.0.1.dist-info/LICENSE
vqa_cimod-0.0.1.dist-info/METADATA
vqa_cimod-0.0.1.dist-info/WHEEL
vqa_cimod-0.0.1.dist-info/top_level.txt
vqa_cimod-0.0.1.dist-info/RECORD
