Metadata-Version: 2.1
Name: vqa-cimod
Version: 0.0.1
Summary: "Framework for the Ising model and QUBO."
Home-page: https://v-quantum-technology.com
Author: "V-QUANTUM JSC"
Author-email: nqthinh@v-quantum-technology.com
License: "Apache License 2.0"
Project-URL: Source, https://github.com/v-quantum-jsc/V-QUANTUM-ANNEALING
Project-URL: Documentation, https://v_quantum_annealing.github.io/v_quantum_annealing
Project-URL: Reference, https://ref.v_quantum_annealing.org/index.html
Platform: UNKNOWN
Classifier: License :: OSI Approved :: Apache Software License
Classifier: Intended Audience :: Science/Research
Classifier: Programming Language :: Python
Classifier: Programming Language :: Python :: 3.7
Classifier: Programming Language :: Python :: 3.8
Classifier: Programming Language :: Python :: 3.9
Classifier: Programming Language :: Python :: 3.10
Classifier: Programming Language :: Python :: 3 :: Only
Classifier: Programming Language :: Python :: Implementation :: CPython
Classifier: Operating System :: Microsoft :: Windows
Classifier: Operating System :: POSIX
Classifier: Operating System :: Unix
Classifier: Operating System :: MacOS
Requires-Python: <3.11,>=3.7
